yrocr/__init__.py
yrocr/cli.py
yrocr/config.py
yrocr/ocr_base.py
yrocr/ocr_fixed_format_file.py
yrocr/ocr_table.py
yrocr/ocr_text.py
yrocr/post_process.py
yrocr/template.py
yrocr/resources/__init__.py
yrocr/resources/format_file_code_converter.py
yrocr/resources/fonts/simfang.ttf
yrocr/resources/post_process/__init__.py
yrocr/resources/post_process/air_transport.py
yrocr/resources/post_process/base.py
yrocr/resources/post_process/idcard.py
yrocr/resources/post_process/idcard_front.py
yrocr/resources/post_process/idcard_reverse.py
yrocr/resources/post_process/invoice_base.py
yrocr/resources/post_process/train_ticket.py
yrocr/resources/post_process/util.py
yrocr/resources/post_process/vat_ele_normal_invoice.py
yrocr/resources/post_process/vat_special_invoice.py
yrocr/resources/post_process/audit/__init__.py
yrocr/resources/post_process/audit/construction_project_reg_cert_shandong.py
yrocr/resources/post_process/audit/construction_works_license_zhejiang.py
yrocr/resources/post_process/audit/ele_facilities_install_license.py
yrocr/resources/post_process/audit/safety_production_license.py
yrocr/resources/post_process/biz_license_three_in_one/__init__.py
yrocr/resources/post_process/biz_license_three_in_one/base_biz_license.py
yrocr/resources/post_process/biz_license_three_in_one/biz_license_a.py
yrocr/resources/post_process/biz_license_three_in_one/biz_license_g.py
yrocr/resources/templates/.DS_Store
yrocr/resources/templates/example.json
yrocr/resources/templates/tpl_air_transport.json
yrocr/resources/templates/tpl_idcard.json
yrocr/resources/templates/tpl_idcard_front.json
yrocr/resources/templates/tpl_idcard_reverse.json
yrocr/resources/templates/tpl_train_ticket.json
yrocr/resources/templates/tpl_vat_ele_normal_invoice.json
yrocr/resources/templates/tpl_vat_special_invoice.json
yrocr/resources/templates/audit/tpl_construction_project_reg_cert_shandong.json
yrocr/resources/templates/audit/tpl_construction_works_license_zhejiang.json
yrocr-0.1.10.dist-info/METADATA
yrocr-0.1.10.dist-info/WHEEL
yrocr-0.1.10.dist-info/entry_points.txt
yrocr-0.1.10.dist-info/top_level.txt
yrocr-0.1.10.dist-info/RECORD
